{
  "datas": [
    {
      "username": "growkings",
      "userid": "1034725351873576990",
      "code": "onX2Z"
    },
    {
      "username": "dek_boy",
      "userid": "1139782740338823199",
      "code": "70S0a"
    },
    {
      "username": "rixboyuwu_v2",
      "userid": "1076916623807619116",
      "code": "hN3x6"
    },
    {
      "username": "jinbei6450",
      "userid": "866944081599135755",
      "code": "Rbok7"
    },
    {
      "username": "cakzgg",
      "userid": "443422981104992258",
      "code": "hnQvj"
    },
    {
      "username": "mscute788",
      "userid": "1122464945234251847",
      "code": "DQulL"
    },
    {
      "username": "vneri.",
      "userid": "449749262842986497",
      "code": "dkKia"
    },
    {
      "username": "sannn2383",
      "userid": "795984874623598592",
      "code": "C2exE"
    },
    {
      "username": "4funs",
      "userid": "393718846361436160",
      "code": "syau6"
    },
    {
      "username": ".axlxx",
      "userid": "994128003820965928",
      "code": "9fWzS"
    },
    {
      "username": "elconner",
      "userid": "759627860536590336",
      "code": "M1Is6"
    },
    {
      "username": "maticparadoxsn",
      "userid": "551284764330688512",
      "code": "uHFYY"
    },
    {
      "username": "kuryam",
      "userid": "396673601979547649",
      "code": "COz4J"
    },
    {
      "username": "ourneed",
      "userid": "1191374263043764325",
      "code": "LEM8N"
    },
    {
      "username": "freeri4e",
      "userid": "910753386465468426",
      "code": "h4M4g"
    },
    {
      "username": "donyhs",
      "userid": "701071473632084049",
      "code": "dHicK"
    },
    {
      "username": "firmanhidayat9",
      "userid": "1077474426259517441",
      "code": "ykxMV"
    },
    {
      "username": "charlierizz",
      "userid": "918837944574435398",
      "code": "X5SzO"
    },
    {
      "username": "riomacanid",
      "userid": "1108730746690084959",
      "code": "1a3lt"
    },
    {
      "username": "renneronero",
      "userid": "684758238968807464",
      "code": "tM8TD"
    },
    {
      "username": "urfavjarr",
      "userid": "913249559717744680",
      "code": "1QFqM"
    },
    {
      "username": "skycore1586",
      "userid": "842093532788293702",
      "code": "bQ79i"
    },
    {
      "username": "mgstoretopup",
      "userid": "775668192613367818",
      "code": "GKCQm"
    },
    {
      "username": "nino1010",
      "userid": "922138009544036373",
      "code": "UIUIf"
    },
    {
      "username": "sawanisasi",
      "userid": "394808448677576706",
      "code": "gJISt"
    },
    {
      "username": "anzurenn",
      "userid": "943056172817219604",
      "code": "XPJj5"
    },
    {
      "username": "cupetzz",
      "userid": "880419381249720350",
      "code": "KnhFv"
    },
    {
      "username": "ayamekdi",
      "userid": "998850474662965300",
      "code": "FmBT8"
    },
    {
      "username": "puuy.",
      "userid": "1052827286623240274",
      "code": "tMrk3"
    },
    {
      "username": "lino5267",
      "userid": "441495599129296896",
      "code": "KMg25"
    },
    {
      "username": "vinixs1873",
      "userid": "960008082493145178",
      "code": "A0qGd"
    },
    {
      "username": "osimababa",
      "userid": "1203476118171160719",
      "code": "dCzZH"
    },
    {
      "username": "likokuman",
      "userid": "1139937161794293800",
      "code": "W2vPE"
    },
    {
      "username": "hannewera",
      "userid": "1246426277343264779",
      "code": "kOvQo"
    },
    {
      "username": "assasinvunny",
      "userid": "1086243521465421834",
      "code": "UJQA2"
    },
    {
      "username": "wanjay1291",
      "userid": "855439177793011732",
      "code": "TAmH5"
    },
    {
      "username": "notvann",
      "userid": "982194602821947403",
      "code": "UX9Mr"
    },
    {
      "username": "devoreon",
      "userid": "442965848764973066",
      "code": "bspTo"
    },
    {
      "username": "youalreadyknowxd",
      "userid": "1048500020787294212",
      "code": "OBxWk"
    },
    {
      "username": "zagashigabom",
      "userid": "895457620440260649",
      "code": "82W9T"
    },
    {
      "username": "guaad.",
      "userid": "930888128498135100",
      "code": "EGkyu"
    },
    {
      "username": "apitbantaisemua",
      "userid": "1195708345814896670",
      "code": "7PEEK"
    },
    {
      "username": "iamnotwinter.",
      "userid": "583920648821145600",
      "code": "zL3uO"
    },
    {
      "username": "advi_vian",
      "userid": "653055853481558070",
      "code": "eiPjv"
    },
    {
      "username": "syrchease",
      "userid": "754248331546460224",
      "code": "s3nKP"
    },
    {
      "username": "paizz6926",
      "userid": "901295665324371978",
      "code": "gHsmZ"
    },
    {
      "username": "fauzan0068",
      "userid": "409626157022052352",
      "code": "cpbkE"
    },
    {
      "username": "ospet",
      "userid": "871367755532734484",
      "code": "aglV2"
    },
    {
      "username": "sympthc",
      "userid": "592386835007799320",
      "code": "5g8G8"
    },
    {
      "username": "arsansstore",
      "userid": "857985485346570262",
      "code": "jmG6h"
    },
    {
      "username": "guntram_",
      "userid": "916171865716850729",
      "code": "eA8lz"
    },
    {
      "username": "thepied",
      "userid": "537251743168200706",
      "code": "2tzja"
    },
    {
      "username": "donikeren",
      "userid": "232474112801505280",
      "code": "tAE4v"
    },
    {
      "username": "kloots",
      "userid": "690921540274880542",
      "code": "iALpg"
    },
    {
      "username": "zufar17",
      "userid": "1089862323105177600",
      "code": "fxxpu"
    },
    {
      "username": "shikalukiii",
      "userid": "801330274004369429",
      "code": "XQcWC"
    },
    {
      "username": "vess5075",
      "userid": "226960527216082955",
      "code": "oTqeW"
    },
    {
      "username": "bambang_gt",
      "userid": "931702070183079978",
      "code": "p89h7"
    },
    {
      "username": "samd2707",
      "userid": "618053336201166894",
      "code": "wnXFr"
    },
    {
      "username": "lantern132",
      "userid": "616250005849636864",
      "code": "QkmhQ"
    },
    {
      "username": "panooo_",
      "userid": "701680438141517904",
      "code": "KxtaT"
    },
    {
      "username": "danzstorev1",
      "userid": "1060106071873703946",
      "code": "2xZNP"
    },
    {
      "username": "rexery.",
      "userid": "1101542216251494550",
      "code": "U5NQl"
    },
    {
      "username": "iiiiiiiiiicans",
      "userid": "821605902594867201",
      "code": "6SEYY"
    },
    {
      "username": ".estiel",
      "userid": "1103379686446333953",
      "code": "V5cvl"
    },
    {
      "username": "xpts.",
      "userid": "1085480465609265203",
      "code": "WsGQz"
    },
    {
      "username": "akim5559",
      "userid": "637241762397552680",
      "code": "Pv6TR"
    }
  ]
}